{
    "os": "Linux-5.14.0-284.11.1.el9_2_cifs.x86_64-x86_64-with-glibc2.34",
    "python": "3.9.16",
    "heartbeatAt": "2024-12-12T19:08:27.538970",
    "startedAt": "2024-12-12T19:08:26.847435",
    "docker": null,
    "cuda": null,
    "args": [
        "--sweep",
        "--use_wandb"
    ],
    "state": "running",
    "program": "/oscar/home/mali37/bert-qa/main.py",
    "codePathLocal": "main.py",
    "codePath": "main.py",
    "git": {
        "remote": "git@github.com:MuhiimAli/bert-qa.git",
        "commit": "826f10828b342c3db8f821a1b0c9eabe7fc83086"
    },
    "email": "muhiim_ali@brown.edu",
    "root": "/oscar/home/mali37/bert-qa",
    "host": "gpu2005.oscar.ccv.brown.edu",
    "username": "mali37",
    "executable": "/usr/bin/python",
    "cpu_count": 32,
    "cpu_count_logical": 32,
    "cpu_freq": {
        "current": 3503.435312499999,
        "min": 1200.0,
        "max": 3900.0
    },
    "cpu_freq_per_core": [
        {
            "current": 3500.214,
            "min": 1200.0,
            "max": 3900.0
        },
        {
            "current": 3500.044,
            "min": 1200.0,
            "max": 3900.0
        },
        {
            "current": 3500.137,
            "min": 1200.0,
            "max": 3900.0
        },
        {
            "current": 3500.205,
            "min": 1200.0,
            "max": 3900.0
        },
        {
            "current": 3499.877,
            "min": 1200.0,
            "max": 3900.0
        },
        {
            "current": 3499.715,
            "min": 1200.0,
            "max": 3900.0
        },
        {
            "current": 3500.206,
            "min": 1200.0,
            "max": 3900.0
        },
        {
            "current": 3499.217,
            "min": 1200.0,
            "max": 3900.0
        },
        {
            "current": 3501.476,
            "min": 1200.0,
            "max": 3900.0
        },
        {
            "current": 3499.769,
            "min": 1200.0,
            "max": 3900.0
        },
        {
            "current": 3499.969,
            "min": 1200.0,
            "max": 3900.0
        },
        {
            "current": 3499.834,
            "min": 1200.0,
            "max": 3900.0
        },
        {
            "current": 3504.795,
            "min": 1200.0,
            "max": 3900.0
        },
        {
            "current": 3499.506,
            "min": 1200.0,
            "max": 3900.0
        },
        {
            "current": 3500.084,
            "min": 1200.0,
            "max": 3900.0
        },
        {
            "current": 3499.814,
            "min": 1200.0,
            "max": 3900.0
        },
        {
            "current": 3499.495,
            "min": 1200.0,
            "max": 3900.0
        },
        {
            "current": 3501.395,
            "min": 1200.0,
            "max": 3900.0
        },
        {
            "current": 3499.78,
            "min": 1200.0,
            "max": 3900.0
        },
        {
            "current": 3500.124,
            "min": 1200.0,
            "max": 3900.0
        },
        {
            "current": 3499.374,
            "min": 1200.0,
            "max": 3900.0
        },
        {
            "current": 3499.999,
            "min": 1200.0,
            "max": 3900.0
        },
        {
            "current": 3499.88,
            "min": 1200.0,
            "max": 3900.0
        },
        {
            "current": 3499.228,
            "min": 1200.0,
            "max": 3900.0
        },
        {
            "current": 3501.306,
            "min": 1200.0,
            "max": 3900.0
        },
        {
            "current": 3497.966,
            "min": 1200.0,
            "max": 3900.0
        },
        {
            "current": 3501.372,
            "min": 1200.0,
            "max": 3900.0
        },
        {
            "current": 3499.999,
            "min": 1200.0,
            "max": 3900.0
        },
        {
            "current": 3497.525,
            "min": 1200.0,
            "max": 3900.0
        },
        {
            "current": 3501.394,
            "min": 1200.0,
            "max": 3900.0
        },
        {
            "current": 3500.93,
            "min": 1200.0,
            "max": 3900.0
        },
        {
            "current": 3505.501,
            "min": 1200.0,
            "max": 3900.0
        }
    ],
    "disk": {
        "/": {
            "total": 187.77203750610352,
            "used": 8.120967864990234
        }
    },
    "gpu": "Quadro RTX 6000",
    "gpu_count": 1,
    "gpu_devices": [
        {
            "name": "Quadro RTX 6000",
            "memory_total": 25769803776
        }
    ],
    "memory": {
        "total": 375.54407501220703
    }
}
